hydra_plugins/random_sweeper_plugin/__init__.py
hydra_plugins/random_sweeper_plugin/py.typed
hydra_plugins/random_sweeper_plugin/random_sweeper.py
hydra_random_sweeper-1.0.1.dist-info/METADATA
hydra_random_sweeper-1.0.1.dist-info/WHEEL
hydra_random_sweeper-1.0.1.dist-info/top_level.txt
hydra_random_sweeper-1.0.1.dist-info/RECORD
